{"get":"players\/squads","parameters":{"team":"1101"},"errors":[],"results":1,"paging":{"current":1,"total":1},"response":[{"team":{"id":1101,"name":"Estonia","logo":"https:\/\/media.api-sports.io\/football\/teams\/1101.png"},"players":[{"id":169295,"name":"K. Hein","age":23,"number":1,"position":"Goalkeeper","photo":"https:\/\/media.api-sports.io\/football\/players\/169295.png"},{"id":39302,"name":"M. Igonen","age":29,"number":12,"position":"Goalkeeper","photo":"https:\/\/media.api-sports.io\/football\/players\/39302.png"},{"id":60795,"name":"K. Vallner","age":27,"number":22,"position":"Goalkeeper","photo":"https:\/\/media.api-sports.io\/football\/players\/60795.png"},{"id":200597,"name":"K. Hussar","age":23,"number":null,"position":"Defender","photo":"https:\/\/media.api-sports.io\/football\/players\/200597.png"},{"id":55909,"name":"M. Kuusk","age":29,"number":null,"position":"Defender","photo":"https:\/\/media.api-sports.io\/football\/players\/55909.png"},{"id":60353,"name":"M. Paskot\u0161i","age":22,"number":3,"position":"Defender","photo":"https:\/\/media.api-sports.io\/football\/players\/60353.png"},{"id":60627,"name":"R. Peetson","age":30,"number":null,"position":"Defender","photo":"https:\/\/media.api-sports.io\/football\/players\/60627.png"},{"id":60685,"name":"J. Saliste","age":30,"number":3,"position":"Defender","photo":"https:\/\/media.api-sports.io\/football\/players\/60685.png"},{"id":60378,"name":"M. Schj\u00f8nning-Larsen","age":24,"number":19,"position":"Defender","photo":"https:\/\/media.api-sports.io\/football\/players\/60378.png"},{"id":40204,"name":"J. Tamm","age":33,"number":16,"position":"Defender","photo":"https:\/\/media.api-sports.io\/football\/players\/40204.png"},{"id":60486,"name":"T. Tammik","age":23,"number":19,"position":"Defender","photo":"https:\/\/media.api-sports.io\/football\/players\/60486.png"},{"id":60358,"name":"M. Ainsalu","age":29,"number":null,"position":"Midfielder","photo":"https:\/\/media.api-sports.io\/football\/players\/60358.png"},{"id":314315,"name":"D. Jepihhin","age":20,"number":null,"position":"Midfielder","photo":"https:\/\/media.api-sports.io\/football\/players\/314315.png"},{"id":55911,"name":"M. K\u00e4it","age":27,"number":4,"position":"Midfielder","photo":"https:\/\/media.api-sports.io\/football\/players\/55911.png"},{"id":357667,"name":"P. Kristal","age":18,"number":14,"position":"Attacker","photo":"https:\/\/media.api-sports.io\/football\/players\/357667.png"},{"id":60613,"name":"M. Miller","age":28,"number":17,"position":"Midfielder","photo":"https:\/\/media.api-sports.io\/football\/players\/60613.png"},{"id":196901,"name":"K. Palumets","age":23,"number":10,"position":"Midfielder","photo":"https:\/\/media.api-sports.io\/football\/players\/196901.png"},{"id":60370,"name":"M. Poom","age":26,"number":null,"position":"Midfielder","photo":"https:\/\/media.api-sports.io\/football\/players\/60370.png"},{"id":208780,"name":"R. Saarma","age":24,"number":7,"position":"Midfielder","photo":"https:\/\/media.api-sports.io\/football\/players\/208780.png"},{"id":60616,"name":"V. Sinyavskiy","age":29,"number":23,"position":"Midfielder","photo":"https:\/\/media.api-sports.io\/football\/players\/60616.png"},{"id":126756,"name":"M. Soomets","age":25,"number":8,"position":"Midfielder","photo":"https:\/\/media.api-sports.io\/football\/players\/126756.png"},{"id":34248,"name":"H. Anier","age":35,"number":8,"position":"Attacker","photo":"https:\/\/media.api-sports.io\/football\/players\/34248.png"},{"id":37470,"name":"R. Sappinen","age":29,"number":15,"position":"Attacker","photo":"https:\/\/media.api-sports.io\/football\/players\/37470.png"},{"id":60676,"name":"A. Tamm","age":24,"number":21,"position":"Attacker","photo":"https:\/\/media.api-sports.io\/football\/players\/60676.png"},{"id":190100,"name":"I. Yakovlev","age":27,"number":9,"position":"Midfielder","photo":"https:\/\/media.api-sports.io\/football\/players\/190100.png"},{"id":39211,"name":"Taijo Teniste","age":37,"number":23,"position":"Defender","photo":"https:\/\/media.api-sports.io\/football\/players\/39211.png"},{"id":60371,"name":"Rocco Robert Shein","age":22,"number":5,"position":"Midfielder","photo":"https:\/\/media.api-sports.io\/football\/players\/60371.png"},{"id":55914,"name":"Konstantin Vassiljev","age":41,"number":14,"position":"Midfielder","photo":"https:\/\/media.api-sports.io\/football\/players\/55914.png"},{"id":11168,"name":"Edgar Tur","age":29,"number":20,"position":"Defender","photo":"https:\/\/media.api-sports.io\/football\/players\/11168.png"},{"id":356604,"name":"Karel Eerme","age":21,"number":26,"position":"Attacker","photo":"https:\/\/media.api-sports.io\/football\/players\/356604.png"},{"id":48142,"name":"Karol Mets","age":32,"number":18,"position":"Defender","photo":"https:\/\/media.api-sports.io\/football\/players\/48142.png"},{"id":60655,"name":"Henri Perk","age":26,"number":22,"position":"Goalkeeper","photo":"https:\/\/media.api-sports.io\/football\/players\/60655.png"},{"id":60802,"name":"Martin Vetkal","age":21,"number":20,"position":"Midfielder","photo":"https:\/\/media.api-sports.io\/football\/players\/60802.png"},{"id":574821,"name":"Karel Mustmaa","age":null,"number":11,"position":"Attacker","photo":"https:\/\/media.api-sports.io\/football\/players\/574821.png"},{"id":564761,"name":"M. Paalberg","age":null,"number":13,"position":"Attacker","photo":"https:\/\/media.api-sports.io\/football\/players\/564761.png"}]}]}